MANIFEST.in
setup.cfg
setup.py
django_restricted_resource/__init__.py
django_restricted_resource/managers.py
django_restricted_resource/models.py
django_restricted_resource/test_utils.py
django_restricted_resource/tests.py
django_restricted_resource/utils.py
django_restricted_resource.egg-info/PKG-INFO
django_restricted_resource.egg-info/SOURCES.txt
django_restricted_resource.egg-info/dependency_links.txt
django_restricted_resource.egg-info/requires.txt
django_restricted_resource.egg-info/top_level.txt
django_restricted_resource.egg-info/zip-safe
django_restricted_resource/test_project/__init__.py
django_restricted_resource/test_project/manage.py
django_restricted_resource/test_project/settings.py
django_restricted_resource/test_project/tests.py