Metadata-Version: 1.1
Name: django-restricted-resource
Version: 2016.8
Summary: Base model for Django that adds simple and efficient ownership and access control.
Home-page: http://git.linaro.org/git/lava/django-restricted-resource.git
Author: Linaro Limited
Author-email: lava-team@linaro.org
License: LGPLv3
Keywords: django,ownership,models
Platform: UNKNOWN
Classifier: Development Status :: 4 - Beta
Classifier: Environment :: Web Environment
Classifier: Framework :: Django
Classifier: Intended Audience :: Developers
Classifier: License :: OSI Approved :: GNU Library or Lesser General Public License (LGPL)
Classifier: Operating System :: OS Independent
Classifier: Programming Language :: Python :: 2.7
Classifier: Programming Language :: Python :: 3.5
